libris/__init__.py
libris/__main__.py
libris/json-schemas/config-schema.json
libris/json-schemas/decorator-schema.json
libris/json-schemas/source-schema.json
libris/json-schemas/sources-schema.json
libris/json-schemas/style-schema.json
libris/json-schemas/styles-schema.json
libris/lib/__init__.py
libris/lib/constants.py
libris/lib/data_extractors.py
libris/lib/pdf_builder.py
libris/lib/watch.py
libris-1.4.0.data/scripts/libris
libris-1.4.0.dist-info/LICENSE.txt
libris-1.4.0.dist-info/METADATA
libris-1.4.0.dist-info/WHEEL
libris-1.4.0.dist-info/top_level.txt
libris-1.4.0.dist-info/RECORD
